pymechlab/__init__.py
pymechlab/classes/__init__.py
pymechlab/classes/batchresult.py
pymechlab/classes/cmh17statistics.py
pymechlab/classes/specimenresult.py
pymechlab/classes/statistics.py
pymechlab/tools/__init__.py
pymechlab/tools/json.py
pymechlab/tools/stats.py
pymechlab-0.1.0.dist-info/licenses/LICENSE
pymechlab-0.1.0.dist-info/METADATA
pymechlab-0.1.0.dist-info/WHEEL
pymechlab-0.1.0.dist-info/top_level.txt
pymechlab-0.1.0.dist-info/RECORD
