Metadata-Version: 2.4
Name: pymechlab
Version: 0.1.0
Summary: Python Package for Mechanical Laboratory Testing
Author-email: Xero64 <xero64@gmail.com>
License-Expression: MIT
Project-URL: Homepage, https://github.com/Xero64/pymechlab
Project-URL: Issues, https://github.com/Xero64/pymechlab/issues
Classifier: Programming Language :: Python :: 3
Classifier: Operating System :: OS Independent
Requires-Python: >=3.10
License-File: LICENSE
Requires-Dist: matplotlib>=3.10.6
Requires-Dist: numpy>=2.2.6
Requires-Dist: py2md>=0.1.3
Requires-Dist: scipy>=1.15.3
Requires-Dist: toleranceinterval>=1.0.3
Dynamic: license-file
